<?xml version="1.0" encoding="UTF-8"?><change>
  <id>f4114530-763e-44dd-9f40-aa65492e9aab</id>
  <lastModified>2015-04-15 11:48:31</lastModified>
  <parentId>28136aec-eb10-471a-b549-dd462e7e845a-1</parentId>
  <userId>a3a6bfc9-f4f3-4283-b9d1-c61481b05f30</userId>
  <dateAndTime>2015-04-15 11:48:31</dateAndTime>
  <key>description</key>
  <newValue>

* Als Nutzer moechte ich einen anderen Nutzer zu meinen Kontakten hinzufuegen

Damit ich mit diesem Nutzer in kontakt bleiben kann.
Dies gibt mir die Moeglichkeit spaeter Aufgaben oder Termine mit ihm zu tauschen, oder eine Aufgabe fuer ihn zu erstellen.
</newValue>
</change>